zoom_chat_anonymizer/__init__.py
zoom_chat_anonymizer/classes/__init__.py
zoom_chat_anonymizer/classes/artemis.py
zoom_chat_anonymizer/classes/message.py
zoom_chat_anonymizer/classes/pause.py
zoom_chat_anonymizer/logic/__init__.py
zoom_chat_anonymizer/logic/anonymize_chat.py
zoom_chat_anonymizer/logic/clean_artemis_file.py
zoom_chat_anonymizer/logic/create_html_from_markdown.py
zoom_chat_anonymizer/logic/create_pdf_from_markdown.py
zoom_chat_anonymizer/logic/sort_moodle_csv.py
zoom_chat_anonymizer/main.py
zoom_chat_anonymizer-0.1.9.dist-info/entry_points.txt
zoom_chat_anonymizer-0.1.9.dist-info/LICENSE
zoom_chat_anonymizer-0.1.9.dist-info/WHEEL
zoom_chat_anonymizer-0.1.9.dist-info/METADATA
zoom_chat_anonymizer-0.1.9.dist-info/RECORD
