Metadata-Version: 2.1
Name: zoom-chat-anonymizer
Version: 0.1.9
Summary: 
Home-page: https://github.com/pstoeckle/Zoom-Chat-Anonymizer.git
License: Apache-2.0
Author: Patrick Stoeckle
Author-email: patrick.stoeckle@posteo.de
Maintainer: Patrick Stöckle
Maintainer-email: patrick.stoeckle@posteo.de
Requires-Python: >=3.8,<4.0
Classifier: License :: OSI Approved :: Apache Software License
Classifier: Programming Language :: Python :: 3
Classifier: Programming Language :: Python :: 3.8
Classifier: Programming Language :: Python :: 3.9
Classifier: Programming Language :: Python :: 3.10
Classifier: Programming Language :: Python :: 3.11
Requires-Dist: typer (>=0.7.0,<0.8.0)
Project-URL: Repository, https://github.com/pstoeckle/Zoom-Chat-Anonymizer.git
